{
  "project_info": {
    "project_number": "94674385670",
    "project_id": "tic-tac-toe-firebase-ae6a6",
    "storage_bucket": "tic-tac-toe-firebase-ae6a6.appspot.com"
  },
  "client": [
    {
      "client_info": {
        "mobilesdk_app_id": "1:94674385670:android:7fe04bf51665c7a3f13c87",
        "android_client_info": {
          "package_name": "com.unal.edu.androidfirebase"
        }
      },
      "oauth_client": [],
      "api_key": [
        {
          "current_key": "AIzaSyBkjbPcAzP4P5aLm49E_FQnd9Rhiw_fM3g"
        }
      ],
      "services": {
        "appinvite_service": {
          "other_platform_oauth_client": []
        }
      }
    }
  ],
  "configuration_version": "1"
}